stackclient/client.py
stackclient/exceptions.py
stackclient-0.2.4.dist-info/licenses/LICENSE
stackclient-0.2.4.dist-info/METADATA
stackclient-0.2.4.dist-info/WHEEL
stackclient-0.2.4.dist-info/top_level.txt
stackclient-0.2.4.dist-info/RECORD
