Metadata-Version: 2.4
Name: stackclient
Version: 0.2.4
Summary: Python library to interact with Stackspot Agents API
Requires-Python: >=3.13
License-File: LICENSE
Requires-Dist: urllib3>=2.5.0
Dynamic: license-file
